AUTHORS
CHANGES
INSTALL
LICENCE
MANIFEST.in
README
setup.py
binomia_translatable_multilevel_menu.egg-info/PKG-INFO
binomia_translatable_multilevel_menu.egg-info/SOURCES.txt
binomia_translatable_multilevel_menu.egg-info/dependency_links.txt
binomia_translatable_multilevel_menu.egg-info/not-zip-safe
binomia_translatable_multilevel_menu.egg-info/top_level.txt
menu/__init__.py
menu/admin.py
menu/models.py
menu/tests.py
menu/views.py
menu/templates/menu.html
menu/templates/submenu.html
menu/templatetags/__init__.py
menu/templatetags/menubuilder.py