Metadata-Version: 1.0
Name: binomia-translatable-multilevel-menu
Version: 0.0.6
Summary: Simple translatable multilevel menu system.
Home-page: http://packages.python.org/binomia_translatable_multilevel_menu
Author: Binomia SC
Author-email: samuel.barrado@binomia.es
License: BSD
Keywords: translatable multilevel menu
Platform: UNKNOWN
Classifier: Development Status :: 3 - Alpha
Classifier: Topic :: Utilities
Classifier: License :: OSI Approved :: BSD License
